{"external_urls":{"spotify":"https://open.spotify.com/playlist/37i9dQZF1DWZd79rJ6a7lp"},"tracks":{"items":[{"track":{"artists":[{"name":"Eternalistic"}],"external_urls":{"spotify":"https://open.spotify.com/track/0TT2Tzi8mEETCqYZ1ffiHh"},"explicit":false,"name":"Serene Reflections","id":"0TT2Tzi8mEETCqYZ1ffiHh"}},{"track":{"artists":[{"name":"Somnum Magnam"}],"external_urls":{"spotify":"https://open.spotify.com/track/6KzdWw8Hi1bz1lVw2AXDzb"},"explicit":false,"name":"Touches","id":"6KzdWw8Hi1bz1lVw2AXDzb"}},{"track":{"artists":[{"name":"Luna Novina"}],"external_urls":{"spotify":"https://open.spotify.com/track/5PFe4q5VmBRaYUnXSeZ6EX"},"explicit":false,"name":"Aeterna","id":"5PFe4q5VmBRaYUnXSeZ6EX"}},{"track":{"artists":[{"name":"Leander Vaughn"}],"external_urls":{"spotify":"https://open.spotify.com/track/14BiZ33a6hZeAw3NWtRbl0"},"explicit":false,"name":"Onto","id":"14BiZ33a6hZeAw3NWtRbl0"}},{"track":{"artists":[{"name":"Jody R"}],"external_urls":{"spotify":"https://open.spotify.com/track/0T6MlMNUB10hPTou6NaMRL"},"explicit":false,"name":"Emotional privilege","id":"0T6MlMNUB10hPTou6NaMRL"}},{"track":{"artists":[{"name":"Placidous"}],"external_urls":{"spotify":"https://open.spotify.com/track/6SbFBs5pon9flXihCWlfO4"},"explicit":false,"name":"Ara","id":"6SbFBs5pon9flXihCWlfO4"}},{"track":{"artists":[{"name":"Starshine Strum"}],"external_urls":{"spotify":"https://open.spotify.com/track/0LEzTG4JEiFgNg6XbgGQh2"},"explicit":false,"name":"Anthazit Plastics","id":"0LEzTG4JEiFgNg6XbgGQh2"}},{"track":{"artists":[{"name":"Rufus Ziegler"}],"external_urls":{"spotify":"https://open.spotify.com/track/0KXcQySPBhAvDT5c6J1KxH"},"explicit":false,"name":"Essence","id":"0KXcQySPBhAvDT5c6J1KxH"}},{"track":{"artists":[{"name":"Celestros"}],"external_urls":{"spotify":"https://open.spotify.com/track/79VaizbXk2cpZy3nzUxjN7"},"explicit":false,"name":"Slumber","id":"79VaizbXk2cpZy3nzUxjN7"}},{"track":{"artists":[{"name":"Decanõe"}],"external_urls":{"spotify":"https://open.spotify.com/track/74uFbc3D8QpxBn5CObGShi"},"explicit":false,"name":"Existing","id":"74uFbc3D8QpxBn5CObGShi"}},{"track":{"artists":[{"name":"Nova Issue"}],"external_urls":{"spotify":"https://open.spotify.com/track/4lQzFqLkWkySwksrnuwIUn"},"explicit":false,"name":"Imagination","id":"4lQzFqLkWkySwksrnuwIUn"}},{"track":{"artists":[{"name":"Eône"}],"external_urls":{"spotify":"https://open.spotify.com/track/6qEnfDbUi83vhDsQ0Fbft1"},"explicit":false,"name":"Enhance","id":"6qEnfDbUi83vhDsQ0Fbft1"}},{"track":{"artists":[{"name":"Elvio Martín"}],"external_urls":{"spotify":"https://open.spotify.com/track/2ql3MvEcsA946YC2Ob0sQc"},"explicit":false,"name":"abundance","id":"2ql3MvEcsA946YC2Ob0sQc"}},{"track":{"artists":[{"name":"Imperial Atlas"}],"external_urls":{"spotify":"https://open.spotify.com/track/3RYIdSIZeNZMqCZznqOTO7"},"explicit":false,"name":"Embrace","id":"3RYIdSIZeNZMqCZznqOTO7"}},{"track":{"artists":[{"name":"Leon White"}],"external_urls":{"spotify":"https://open.spotify.com/track/7ybzymL0w0XYyJaBeqFSRy"},"explicit":false,"name":"Placid Echoes","id":"7ybzymL0w0XYyJaBeqFSRy"}},{"track":{"artists":[{"name":"Furna"}],"external_urls":{"spotify":"https://open.spotify.com/track/6RA2OBqaRhntWewbRaFkQQ"},"explicit":false,"name":"Frozen waves","id":"6RA2OBqaRhntWewbRaFkQQ"}},{"track":{"artists":[{"name":"Olivia Line"}],"external_urls":{"spotify":"https://open.spotify.com/track/7GKuF5uVs0dGmjWzoA5VW5"},"explicit":false,"name":"Translucent night","id":"7GKuF5uVs0dGmjWzoA5VW5"}},{"track":{"artists":[{"name":"Relaxatron"}],"external_urls":{"spotify":"https://open.spotify.com/track/7x5R8CCs2hpUWdReDxsQYZ"},"explicit":false,"name":"Resort To Nature","id":"7x5R8CCs2hpUWdReDxsQYZ"}},{"track":{"artists":[{"name":"Garcíia"}],"external_urls":{"spotify":"https://open.spotify.com/track/2kTefS4HKaVn1URttI7UyG"},"explicit":false,"name":"Continual","id":"2kTefS4HKaVn1URttI7UyG"}},{"track":{"artists":[{"name":"Baba Hall"}],"external_urls":{"spotify":"https://open.spotify.com/track/1Hue36yxMqCh9xX6TQ39pP"},"explicit":false,"name":"Balance Of Life","id":"1Hue36yxMqCh9xX6TQ39pP"}},{"track":{"artists":[{"name":"Zephyrical"}],"external_urls":{"spotify":"https://open.spotify.com/track/44RKtm5CchIPJKwVikNbVB"},"explicit":false,"name":"Theremant","id":"44RKtm5CchIPJKwVikNbVB"}},{"track":{"artists":[{"name":"Eldrelder"}],"external_urls":{"spotify":"https://open.spotify.com/track/07KybtBPaFyyZY9c5TiLpy"},"explicit":false,"name":"Elevation","id":"07KybtBPaFyyZY9c5TiLpy"}},{"track":{"artists":[{"name":"Puddle of Head"}],"external_urls":{"spotify":"https://open.spotify.com/track/2d0qDRQAsyxsEPr6671Y9X"},"explicit":false,"name":"Return Home","id":"2d0qDRQAsyxsEPr6671Y9X"}},{"track":{"artists":[{"name":"Sol Reya"}],"external_urls":{"spotify":"https://open.spotify.com/track/2y2u04LUbceXkEcUndxo1N"},"explicit":false,"name":"Serendipity","id":"2y2u04LUbceXkEcUndxo1N"}},{"track":{"artists":[{"name":"Celestial Aura"}],"external_urls":{"spotify":"https://open.spotify.com/track/4EfWUdmaf5KMHHuXVchEU9"},"explicit":false,"name":"A Special Place","id":"4EfWUdmaf5KMHHuXVchEU9"}},{"track":{"artists":[{"name":"Wicker Whales"}],"external_urls":{"spotify":"https://open.spotify.com/track/1d0sc4npZeCAxX4YRuaCNG"},"explicit":false,"name":"Come Wander","id":"1d0sc4npZeCAxX4YRuaCNG"}},{"track":{"artists":[{"name":"Everlasting Theta"}],"external_urls":{"spotify":"https://open.spotify.com/track/7nV2HPhYAWLBtJ2JCUyYfx"},"explicit":false,"name":"Singularity","id":"7nV2HPhYAWLBtJ2JCUyYfx"}},{"track":{"artists":[{"name":"Hello Artemisia!"}],"external_urls":{"spotify":"https://open.spotify.com/track/7ygS19lO68LzUmz355qp3S"},"explicit":false,"name":"Les dormeurs","id":"7ygS19lO68LzUmz355qp3S"}},{"track":{"artists":[{"name":"Ursae Minoris"}],"external_urls":{"spotify":"https://open.spotify.com/track/1rJg3BtPS7AuK2oKJKS0Ds"},"explicit":false,"name":"Harvest Moon","id":"1rJg3BtPS7AuK2oKJKS0Ds"}},{"track":{"artists":[{"name":"Sleep Advisor"}],"external_urls":{"spotify":"https://open.spotify.com/track/6s5TgRuS940qXdSCR2Lyos"},"explicit":false,"name":"Repose","id":"6s5TgRuS940qXdSCR2Lyos"}},{"track":{"artists":[{"name":"Bedtime Muse"}],"external_urls":{"spotify":"https://open.spotify.com/track/20hO8nLj0SFWfC2b2d0Czs"},"explicit":false,"name":"Magical Calmness","id":"20hO8nLj0SFWfC2b2d0Czs"}},{"track":{"artists":[{"name":"Riseran"}],"external_urls":{"spotify":"https://open.spotify.com/track/1ayIzU9MXiMUd1MWAJP2Y7"},"explicit":false,"name":"Signs In The Sky","id":"1ayIzU9MXiMUd1MWAJP2Y7"}},{"track":{"artists":[{"name":"Don Salfva"}],"external_urls":{"spotify":"https://open.spotify.com/track/4C97XW6FKoCdgyXoTgB6bV"},"explicit":false,"name":"Barefoot","id":"4C97XW6FKoCdgyXoTgB6bV"}},{"track":{"artists":[{"name":"Deep Vibrations"}],"external_urls":{"spotify":"https://open.spotify.com/track/7z59OYsoOTguktR8aHASAD"},"explicit":false,"name":"Emancipation","id":"7z59OYsoOTguktR8aHASAD"}},{"track":{"artists":[{"name":"Arietis"}],"external_urls":{"spotify":"https://open.spotify.com/track/5yCIRoiQ4DatjmySLxm20e"},"explicit":false,"name":"Definite","id":"5yCIRoiQ4DatjmySLxm20e"}},{"track":{"artists":[{"name":"Amphose"}],"external_urls":{"spotify":"https://open.spotify.com/track/6sCBSdY0rB7pwS8kosA2Md"},"explicit":false,"name":"Endicino","id":"6sCBSdY0rB7pwS8kosA2Md"}},{"track":{"artists":[{"name":"Celestelle"}],"external_urls":{"spotify":"https://open.spotify.com/track/72PXvumKV3t0Eip3D8vkM4"},"explicit":false,"name":"Stardust Memories","id":"72PXvumKV3t0Eip3D8vkM4"}},{"track":{"artists":[{"name":"Silas Luminance"}],"external_urls":{"spotify":"https://open.spotify.com/track/5ypeecxfih2hBteQ4DWPY6"},"explicit":false,"name":"Look To The East","id":"5ypeecxfih2hBteQ4DWPY6"}},{"track":{"artists":[{"name":"Eternalistic"}],"external_urls":{"spotify":"https://open.spotify.com/track/6SFSWBUYfepFU3iNlXLPeu"},"explicit":false,"name":"Solstice Waves","id":"6SFSWBUYfepFU3iNlXLPeu"}},{"track":{"artists":[{"name":"Arnór"}],"external_urls":{"spotify":"https://open.spotify.com/track/3m8XZRHnycaVI6hA1CDuBC"},"explicit":false,"name":"ÚðI","id":"3m8XZRHnycaVI6hA1CDuBC"}},{"track":{"artists":[{"name":"different spaces"}],"external_urls":{"spotify":"https://open.spotify.com/track/0v4OsqxNQmqxaz10teJsWO"},"explicit":false,"name":"Include","id":"0v4OsqxNQmqxaz10teJsWO"}},{"track":{"artists":[{"name":"Chakra Tides"}],"external_urls":{"spotify":"https://open.spotify.com/track/5xcMiHMYeXbjdcYUDYzZzL"},"explicit":false,"name":"Etherealism","id":"5xcMiHMYeXbjdcYUDYzZzL"}},{"track":{"artists":[{"name":"Huma"}],"external_urls":{"spotify":"https://open.spotify.com/track/3uZ4KyVZwwnfAt3IGhS3c0"},"explicit":false,"name":"Animálico","id":"3uZ4KyVZwwnfAt3IGhS3c0"}},{"track":{"artists":[{"name":"A´leroi"}],"external_urls":{"spotify":"https://open.spotify.com/track/2rAClrs2LgdQiO1w7sczaS"},"explicit":false,"name":"Occasion","id":"2rAClrs2LgdQiO1w7sczaS"}},{"track":{"artists":[{"name":"Ganlas"}],"external_urls":{"spotify":"https://open.spotify.com/track/5rDK66Zorl6x02BmupEFbM"},"explicit":false,"name":"Solsten","id":"5rDK66Zorl6x02BmupEFbM"}},{"track":{"artists":[{"name":"Aveniós"}],"external_urls":{"spotify":"https://open.spotify.com/track/13c21xph1VSr6Nxc5JSMeP"},"explicit":false,"name":"Expectancy","id":"13c21xph1VSr6Nxc5JSMeP"}},{"track":{"artists":[{"name":"Leo Mano"}],"external_urls":{"spotify":"https://open.spotify.com/track/3g6uL1itMFGwt7I4ZL93BB"},"explicit":false,"name":"Dreaming Away","id":"3g6uL1itMFGwt7I4ZL93BB"}},{"track":{"artists":[{"name":"Ageena"}],"external_urls":{"spotify":"https://open.spotify.com/track/7pj05Z3J520aOzLdH3sAAz"},"explicit":false,"name":"Permanence","id":"7pj05Z3J520aOzLdH3sAAz"}},{"track":{"artists":[{"name":"Hirenth"}],"external_urls":{"spotify":"https://open.spotify.com/track/4baX3QPYxpxQN6EZb8xhDq"},"explicit":false,"name":"Mox","id":"4baX3QPYxpxQN6EZb8xhDq"}},{"track":{"artists":[{"name":"Cosmici"}],"external_urls":{"spotify":"https://open.spotify.com/track/06aTU7D4kaQd5rdSsfe5Ck"},"explicit":false,"name":"Hydrogen","id":"06aTU7D4kaQd5rdSsfe5Ck"}},{"track":{"artists":[{"name":"Edge Of The Spiral"}],"external_urls":{"spotify":"https://open.spotify.com/track/3qW4n7ZcKKdby0Hyp0tVma"},"explicit":false,"name":"Aetheris","id":"3qW4n7ZcKKdby0Hyp0tVma"}},{"track":{"artists":[{"name":"Aksel Møller"}],"external_urls":{"spotify":"https://open.spotify.com/track/3IVrwyHQPdZBchIDkPHfZf"},"explicit":false,"name":"Verdensrommet","id":"3IVrwyHQPdZBchIDkPHfZf"}},{"track":{"artists":[{"name":"Avieone"}],"external_urls":{"spotify":"https://open.spotify.com/track/4u8gHl3MrLMeQN0JDhDJvr"},"explicit":false,"name":"Ideal","id":"4u8gHl3MrLMeQN0JDhDJvr"}},{"track":{"artists":[{"name":"Erlah"}],"external_urls":{"spotify":"https://open.spotify.com/track/0mIZucxdkk7uAbQi06ZhA6"},"explicit":false,"name":"Serenity","id":"0mIZucxdkk7uAbQi06ZhA6"}},{"track":{"artists":[{"name":"Tuscany Flow"}],"external_urls":{"spotify":"https://open.spotify.com/track/5y6Cy93KwBgAuL2Il5YXN7"},"explicit":false,"name":"Stress Reliever","id":"5y6Cy93KwBgAuL2Il5YXN7"}},{"track":{"artists":[{"name":"iavú"}],"external_urls":{"spotify":"https://open.spotify.com/track/0AC6SZlAoEbvzhMeUiwsAq"},"explicit":false,"name":"Stabilize","id":"0AC6SZlAoEbvzhMeUiwsAq"}},{"track":{"artists":[{"name":"X-Genie"}],"external_urls":{"spotify":"https://open.spotify.com/track/3u5XjYs1nfWW53voU5mxpx"},"explicit":false,"name":"Infinitya","id":"3u5XjYs1nfWW53voU5mxpx"}},{"track":{"artists":[{"name":"Miriam van Steeg"}],"external_urls":{"spotify":"https://open.spotify.com/track/3qv6UdZerLnFiGkWBynjGv"},"explicit":false,"name":"Benevolent","id":"3qv6UdZerLnFiGkWBynjGv"}},{"track":{"artists":[{"name":"Enma"}],"external_urls":{"spotify":"https://open.spotify.com/track/2oRPG3rScsUtAwJ5W0Ij6m"},"explicit":false,"name":"Somniantes","id":"2oRPG3rScsUtAwJ5W0Ij6m"}},{"track":{"artists":[{"name":"Benjin Blund"}],"external_urls":{"spotify":"https://open.spotify.com/track/3jpblyEuLgkdrhGm6nKJz5"},"explicit":false,"name":"For a moment","id":"3jpblyEuLgkdrhGm6nKJz5"}},{"track":{"artists":[{"name":"Richter Gravitas"}],"external_urls":{"spotify":"https://open.spotify.com/track/4wEbipetGjPZ1YFGT2v34O"},"explicit":false,"name":"Simulacrum","id":"4wEbipetGjPZ1YFGT2v34O"}},{"track":{"artists":[{"name":"Matheo Lyon"}],"external_urls":{"spotify":"https://open.spotify.com/track/754SxJuLBc50w8O5lc1VqQ"},"explicit":false,"name":"Overcome","id":"754SxJuLBc50w8O5lc1VqQ"}},{"track":{"artists":[{"name":"Sangenjaya"}],"external_urls":{"spotify":"https://open.spotify.com/track/0Ajb3AAzrWvCSo3aMW6mXt"},"explicit":false,"name":"Glaciara","id":"0Ajb3AAzrWvCSo3aMW6mXt"}},{"track":{"artists":[{"name":"Zamphire"}],"external_urls":{"spotify":"https://open.spotify.com/track/78xXqulK9gc4Cfl6zeDoHk"},"explicit":false,"name":"Fauna","id":"78xXqulK9gc4Cfl6zeDoHk"}},{"track":{"artists":[{"name":"Latehours"}],"external_urls":{"spotify":"https://open.spotify.com/track/3b9FmqamhswFKthJpVEGHk"},"explicit":false,"name":"Acknowledge","id":"3b9FmqamhswFKthJpVEGHk"}},{"track":{"artists":[{"name":"Sleepwear"}],"external_urls":{"spotify":"https://open.spotify.com/track/3sunZ2cuWiRtcijRukE8kJ"},"explicit":false,"name":"Perfume","id":"3sunZ2cuWiRtcijRukE8kJ"}},{"track":{"artists":[{"name":"Coseae"}],"external_urls":{"spotify":"https://open.spotify.com/track/27ZLSp1tyjQQpm4doIhFCY"},"explicit":false,"name":"Quietness","id":"27ZLSp1tyjQQpm4doIhFCY"}},{"track":{"artists":[{"name":"Folksaga"}],"external_urls":{"spotify":"https://open.spotify.com/track/1ATwyUWpAnvpCGgsSsQ7Ms"},"explicit":false,"name":"Clairvoyance","id":"1ATwyUWpAnvpCGgsSsQ7Ms"}},{"track":{"artists":[{"name":"Etta"}],"external_urls":{"spotify":"https://open.spotify.com/track/4KHtSL1CTl3mLQUmeS0FzZ"},"explicit":false,"name":"Love and Light","id":"4KHtSL1CTl3mLQUmeS0FzZ"}},{"track":{"artists":[{"name":"myndstream"}],"external_urls":{"spotify":"https://open.spotify.com/track/0E90iMgBCVaX7euZDNIsmE"},"explicit":false,"name":"Paradiso","id":"0E90iMgBCVaX7euZDNIsmE"}},{"track":{"artists":[{"name":"Decanõe"}],"external_urls":{"spotify":"https://open.spotify.com/track/6BClTbOxNLsOR3BdQQEahj"},"explicit":false,"name":"Along","id":"6BClTbOxNLsOR3BdQQEahj"}},{"track":{"artists":[{"name":"Kotono Tanaka"}],"external_urls":{"spotify":"https://open.spotify.com/track/1yNQpzSyigQQ91TLZHutvB"},"explicit":false,"name":"Response","id":"1yNQpzSyigQQ91TLZHutvB"}},{"track":{"artists":[{"name":"Latehours"}],"external_urls":{"spotify":"https://open.spotify.com/track/5Xmp3b4vLeOFSf4DEudOqv"},"explicit":false,"name":"Relatively","id":"5Xmp3b4vLeOFSf4DEudOqv"}},{"track":{"artists":[{"name":"Elie Elie"}],"external_urls":{"spotify":"https://open.spotify.com/track/5YOZJuXBLkMiOakT0xi0CA"},"explicit":false,"name":"Northern Vision","id":"5YOZJuXBLkMiOakT0xi0CA"}},{"track":{"artists":[{"name":"Gateway IV"}],"external_urls":{"spotify":"https://open.spotify.com/track/7DqRtx3iWhTVEfPL4feQNs"},"explicit":false,"name":"Soft Corals","id":"7DqRtx3iWhTVEfPL4feQNs"}},{"track":{"artists":[{"name":"Snooze Narrator"}],"external_urls":{"spotify":"https://open.spotify.com/track/7zGEVhbWkkwVeu15l42JCV"},"explicit":false,"name":"Mindful Heights","id":"7zGEVhbWkkwVeu15l42JCV"}},{"track":{"artists":[{"name":"Nova Cantabile"}],"external_urls":{"spotify":"https://open.spotify.com/track/1XOpm9WIEN5yLBH18kh4zf"},"explicit":false,"name":"Atrea & Astrea","id":"1XOpm9WIEN5yLBH18kh4zf"}},{"track":{"artists":[{"name":"Alma Meris"}],"external_urls":{"spotify":"https://open.spotify.com/track/7eKlaWsEYpNPZXLPAXClqf"},"explicit":false,"name":"Gracious","id":"7eKlaWsEYpNPZXLPAXClqf"}},{"track":{"artists":[{"name":"Soul Pursuit"}],"external_urls":{"spotify":"https://open.spotify.com/track/34OU5mx0WLo18srNdK3mr0"},"explicit":false,"name":"Whispering Wind","id":"34OU5mx0WLo18srNdK3mr0"}},{"track":{"artists":[{"name":"Noni Ammin"}],"external_urls":{"spotify":"https://open.spotify.com/track/74RJytYYsMkbWTBPjzgZre"},"explicit":false,"name":"Qadar","id":"74RJytYYsMkbWTBPjzgZre"}},{"track":{"artists":[{"name":"Loe Vida"}],"external_urls":{"spotify":"https://open.spotify.com/track/59s8YAJpSLUMRGzys8B7K4"},"explicit":false,"name":"Soon","id":"59s8YAJpSLUMRGzys8B7K4"}},{"track":{"artists":[{"name":"Eône"}],"external_urls":{"spotify":"https://open.spotify.com/track/2fg3YTYPULVQbfF7RbQqaa"},"explicit":false,"name":"Other","id":"2fg3YTYPULVQbfF7RbQqaa"}},{"track":{"artists":[{"name":"Aurora Novara"}],"external_urls":{"spotify":"https://open.spotify.com/track/5mEstebX16SCW56WWnEluW"},"explicit":false,"name":"Blissful Breeze","id":"5mEstebX16SCW56WWnEluW"}},{"track":{"artists":[{"name":"Joa Abbot"}],"external_urls":{"spotify":"https://open.spotify.com/track/6C5c20UUEJhT8tFhY3kDPe"},"explicit":false,"name":"Restful Whispers","id":"6C5c20UUEJhT8tFhY3kDPe"}},{"track":{"artists":[{"name":"Elysian Lotus"}],"external_urls":{"spotify":"https://open.spotify.com/track/46KDAvVtuSx7tm7FPIN7Vh"},"explicit":false,"name":"Cassiopeia","id":"46KDAvVtuSx7tm7FPIN7Vh"}},{"track":{"artists":[{"name":"Cloudville"}],"external_urls":{"spotify":"https://open.spotify.com/track/2So77BubnnvW58szq8RePp"},"explicit":false,"name":"Myst","id":"2So77BubnnvW58szq8RePp"}},{"track":{"artists":[{"name":"Celestial Whisperer"}],"external_urls":{"spotify":"https://open.spotify.com/track/0GRGJ6N5wWFpDTDqYJCzWU"},"explicit":false,"name":"Dusk's Embrace","id":"0GRGJ6N5wWFpDTDqYJCzWU"}},{"track":{"artists":[{"name":"Benjamin Mounfield"}],"external_urls":{"spotify":"https://open.spotify.com/track/4P3rf7bwHPHVl6w35aE7Ej"},"explicit":false,"name":"Seeking Solace","id":"4P3rf7bwHPHVl6w35aE7Ej"}},{"track":{"artists":[{"name":"Hans Jacob"}],"external_urls":{"spotify":"https://open.spotify.com/track/37PNuXmxQzb7xQERMSoYdA"},"explicit":false,"name":"Endless Cosmos","id":"37PNuXmxQzb7xQERMSoYdA"}},{"track":{"artists":[{"name":"Rama Fiore"}],"external_urls":{"spotify":"https://open.spotify.com/track/54cRF683yoAMcfefg1Drfu"},"explicit":false,"name":"Soft Touch","id":"54cRF683yoAMcfefg1Drfu"}},{"track":{"artists":[{"name":"Ookean"}],"external_urls":{"spotify":"https://open.spotify.com/track/52ahkUIhePPGiz4lvI4Ah9"},"explicit":false,"name":"Dreamwalker","id":"52ahkUIhePPGiz4lvI4Ah9"}},{"track":{"artists":[{"name":"Aca Malvina"}],"external_urls":{"spotify":"https://open.spotify.com/track/0wRgctPH6on0bSgdCO9whG"},"explicit":false,"name":"Himachal","id":"0wRgctPH6on0bSgdCO9whG"}},{"track":{"artists":[{"name":"Moontonic"}],"external_urls":{"spotify":"https://open.spotify.com/track/6wjnlFiyEN25XVYCUsR2TU"},"explicit":false,"name":"Twine","id":"6wjnlFiyEN25XVYCUsR2TU"}},{"track":{"artists":[{"name":"vindi meta"}],"external_urls":{"spotify":"https://open.spotify.com/track/3cKtbvlmZLIGQlvlXVGWcO"},"explicit":false,"name":"unwinding mind","id":"3cKtbvlmZLIGQlvlXVGWcO"}},{"track":{"artists":[{"name":"Author S"}],"external_urls":{"spotify":"https://open.spotify.com/track/5K004QUVvXMTWD97bS8GuF"},"explicit":false,"name":"The Morning Star","id":"5K004QUVvXMTWD97bS8GuF"}},{"track":{"artists":[{"name":"Fleurs de Son"}],"external_urls":{"spotify":"https://open.spotify.com/track/4xEChYDVoW5ZW21kuwUwSD"},"explicit":false,"name":"Daffodilian Dreams","id":"4xEChYDVoW5ZW21kuwUwSD"}},{"track":{"artists":[{"name":"Vígi Seaghdh"}],"external_urls":{"spotify":"https://open.spotify.com/track/1qNDx2ajmcECC1mVzJl3oO"},"explicit":false,"name":"Into The Light","id":"1qNDx2ajmcECC1mVzJl3oO"}},{"track":{"artists":[{"name":"Nessa Wright"}],"external_urls":{"spotify":"https://open.spotify.com/track/1NRLFIhFm333fvUE46FSC2"},"explicit":false,"name":"Let go","id":"1NRLFIhFm333fvUE46FSC2"}},{"track":{"artists":[{"name":"Kaiser Hulenstadt"}],"external_urls":{"spotify":"https://open.spotify.com/track/6i1rajo3ylTTlD3DCITSTo"},"explicit":false,"name":"Sensibility","id":"6i1rajo3ylTTlD3DCITSTo"}},{"track":{"artists":[{"name":"Somnum Magnam"}],"external_urls":{"spotify":"https://open.spotify.com/track/0jZ3SFl1XOHBX7cppGE8YM"},"explicit":false,"name":"Adagioria","id":"0jZ3SFl1XOHBX7cppGE8YM"}}]},"name":"Sleep","description":"Gentle Ambient piano to help you fall asleep. ","id":"37i9dQZF1DWZd79rJ6a7lp","explicit":false}